{
  "url": "https://hk.news.yahoo.com/%E5%AE%8F%E7%A6%8F%E8%8B%91%E4%BA%94%E7%B4%9A%E7%81%AB%EF%BD%9C%E6%89%B9%E8%A9%95%E6%94%BF%E5%BA%9C%E6%96%87%E7%AB%A0%E9%81%AD%E5%A4%A7%E5%85%AC%E5%A0%B1-fb-%E5%B1%A2%E6%94%B9%E5%85%A7%E5%AE%B9%E6%9C%80%E7%B5%82%E5%88%AA%E5%B8%96-%E5%B1%88%E7%A9%8E%E5%A6%8D%E5%9B%9E%E6%87%89%EF%BC%9A%E6%98%AF%E4%BA%BA%E5%AE%B6%E7%9A%84%E8%87%AA%E7%94%B1%EF%BD%9Cyahoo-074846463.html",
  "title": "批評政府文章遭大公報 FB 屢改內容最終刪帖 屈穎妍回應：是人家的自由｜Yahoo",
  "source": "yahoo-news-hk",
  "source_file": "content\\news\\yahoo-news-hk\\README.md",
  "scraped_at": "2025-12-07T14:46:34.970627",
  "archive_path": "content\\news\\yahoo-news-hk\\archive\\批評政府文章遭大公報-fb-屢改內容最終刪帖-屈穎妍回應是人家的自由yahoo"
}